<?xml version="1.0" encoding="utf-8"?>
<Resources Culture="en-US">
	<Group Type="String">
		<Items>
			<Item Name="Caption" Value="Концерты" />
			<Item Name="Columns.UsrActive.Caption" Value="Активный" />
			<Item Name="Columns.UsrCode.Caption" Value="Код" />
			<Item Name="Columns.UsrConcertType.Caption" Value="Тип концерта" />
			<Item Name="Columns.UsrNotes.Caption" Value="Примечания" />
			<Item Name="Columns.UsrOwner.Caption" Value="Ответственный" />
			<Item Name="Columns.UsrTitle.Caption" Value="Name" />
			<Item Name="EventsProcessSchema.Caption" Value="Base object" />
		</Items>
	</Group>
</Resources>